SystemSage/__init__.py
SystemSage/__main__.py
SystemSage/server.py
systemsage-0.1.dist-info/licenses/LICENSE
systemsage-0.1.dist-info/METADATA
systemsage-0.1.dist-info/WHEEL
systemsage-0.1.dist-info/entry_points.txt
systemsage-0.1.dist-info/top_level.txt
systemsage-0.1.dist-info/RECORD
